{
  "type": "forge:conditional",
  "recipes": [
    {
      "conditions": [
        {
          "type": "additionalweapon:config_enable",
          "config_enable": "additionalweapon:iron_spear"
        }
      ],
      "recipe": {
        "type": "minecraft:crafting_shaped",
        "key": {
          "#": {
            "tag": "forge:ingots/iron"
          },
          "/": {
            "item": "additionalweapon:wooden_pole"
          }
        },
        "pattern": [
          " # ",
          " # ",
          " / "
        ],
        "result": {
          "item": "additionalweapon:iron_spear"
        }
      }
    }
  ]
}